channels_binding/__init__.py
channels_binding/actions.py
channels_binding/apps.py
channels_binding/authentification.py
channels_binding/binding.py
channels_binding/consumer.py
channels_binding/consumers.py
channels_binding/permissions.py
channels_binding/request.py
channels_binding/routing.py
channels_binding/routings.py
channels_binding/settings.py
channels_binding/utils.py
channels_binding/bindings/__init__.py
channels_binding/bindings/events.py
channels_binding/bindings/models.py
channels_binding/bindings/registry.py
channels_binding/bindings/serializers.py
channels_binding/bindings/events/__init__.py
channels_binding/bindings/events/delete.py
channels_binding/bindings/events/form.py
channels_binding/bindings/events/list.py
channels_binding/bindings/events/retrieve.py
channels_binding/bindings/events/save.py
channels_binding/bindings/events/search.py
channels_binding/bindings/events/signals.py
tests/__init__.py
tests/models.py
tests/routing.py
tests/test_bindings.py
tests/test_settings.py
tests/tests.py
channels_binding-1.9.8.dist-info/LICENSE
channels_binding-1.9.8.dist-info/METADATA
channels_binding-1.9.8.dist-info/WHEEL
channels_binding-1.9.8.dist-info/top_level.txt
channels_binding-1.9.8.dist-info/RECORD
