Metadata-Version: 1.1
Name: channels_binding
Version: 1.9.8
Summary: a RESTful API Streaming system over django channels, with model binding automations
Home-page: https://github.com/workon-io/channels-binding
Author: Damien Autrusseau
Author-email: damien.autrusseau@gmail.com
License: MIT
Keywords: channels api binding stream models json bindings framework websocket restframework django
Platform: UNKNOWN
Classifier: Development Status :: 3 - Alpha
Classifier: Programming Language :: Python :: 3
Classifier: Programming Language :: Python :: 3.4
Classifier: Programming Language :: Python :: 3.5
Classifier: Programming Language :: Python :: 3.6
Classifier: Programming Language :: Python
Classifier: Topic :: Utilities
Classifier: License :: OSI Approved :: Apache Software License
Classifier: Operating System :: OS Independent
